keras_efficientnet/__init__.py
keras_efficientnet/efficientnet_builder.py
keras_efficientnet/efficientnet_layers.py
keras_efficientnet/efficientnet_model.py
keras_efficientnet/extract_weights.py
keras_efficientnet/keras_model.py
keras_efficientnet/load_weights.py
keras_efficientnet/preprocessing.py
keras_efficientnet/utils.py
keras_efficientnet-0.1.4.dist-info/METADATA
keras_efficientnet-0.1.4.dist-info/WHEEL
keras_efficientnet-0.1.4.dist-info/top_level.txt
keras_efficientnet-0.1.4.dist-info/RECORD
