Metadata-Version: 2.1
Name: keras-efficientnet
Version: 0.1.4
Summary: A Keras implementation of EfficientNet
Home-page: https://github.com/DableUTeeF/keras_efficientnet
Author: Natthaphon Hongcharoen
Author-email: palm22180@gmail.com
License: UNKNOWN
Platform: UNKNOWN
Classifier: Programming Language :: Python :: 3
Classifier: License :: OSI Approved :: MIT License
Classifier: Operating System :: OS Independent
